{
  "experiment": {
    "name": "ARQ_2__ESC_1",
    "timestamp": "2025-06-25T16:25:17.540574",
    "repeat_index": 0
  },
  "effects": {
    "num_taps": {
      "is_categorical": true,
      "bins": null,
      "values": {
        "2": {
          "Éxito": 0.6095377604166666,
          "Error": 0.3904622395833333
        }
      }
    },
    "snr_db": {
      "is_categorical": false,
      "bins": 10,
      "values": {
        "(-0.00268, 0.401]": {
          "Éxito": 0.5977198697068404,
          "Error": 0.4022801302931596
        },
        "(0.401, 0.801]": {
          "Éxito": 0.5898617511520737,
          "Error": 0.41013824884792627
        },
        "(0.801, 1.201]": {
          "Éxito": 0.5459940652818991,
          "Error": 0.4540059347181009
        },
        "(1.201, 1.6]": {
          "Éxito": 0.6122112211221122,
          "Error": 0.38778877887788776
        },
        "(1.6, 2.0]": {
          "Éxito": 0.6419354838709678,
          "Error": 0.3580645161290323
        },
        "(2.0, 2.4]": {
          "Éxito": 0.5783521809369951,
          "Error": 0.42164781906300486
        },
        "(2.4, 2.799]": {
          "Éxito": 0.6434634974533107,
          "Error": 0.3565365025466893
        },
        "(2.799, 3.199]": {
          "Éxito": 0.6291161178509532,
          "Error": 0.3708838821490468
        },
        "(3.199, 3.599]": {
          "Éxito": 0.6179401993355482,
          "Error": 0.38205980066445183
        },
        "(3.599, 3.999]": {
          "Éxito": 0.6503378378378378,
          "Error": 0.34966216216216217
        }
      }
    },
    "phase_offset": {
      "is_categorical": false,
      "bins": 10,
      "values": {
        "(-0.0368, 4.506]": {
          "Éxito": 0.6296900489396411,
          "Error": 0.3703099510603589
        },
        "(4.506, 9.004]": {
          "Éxito": 0.6242038216560509,
          "Error": 0.37579617834394907
        },
        "(9.004, 13.502]": {
          "Éxito": 0.5993485342019544,
          "Error": 0.4006514657980456
        },
        "(13.502, 17.999]": {
          "Éxito": 0.5886178861788618,
          "Error": 0.4113821138211382
        },
        "(17.999, 22.497]": {
          "Éxito": 0.6216216216216216,
          "Error": 0.3783783783783784
        },
        "(22.497, 26.995]": {
          "Éxito": 0.6238095238095238,
          "Error": 0.3761904761904762
        },
        "(26.995, 31.493]": {
          "Éxito": 0.5714285714285714,
          "Error": 0.42857142857142855
        },
        "(31.493, 35.991]": {
          "Éxito": 0.6176961602671118,
          "Error": 0.3823038397328882
        },
        "(35.991, 40.488]": {
          "Éxito": 0.5972927241962775,
          "Error": 0.4027072758037225
        },
        "(40.488, 44.986]": {
          "Éxito": 0.621283255086072,
          "Error": 0.37871674491392804
        }
      }
    },
    "roll_off": {
      "is_categorical": false,
      "bins": 10,
      "values": {
        "(0.2, 0.21]": {
          "Éxito": 0.600326264274062,
          "Error": 0.399673735725938
        },
        "(0.21, 0.22]": {
          "Éxito": 0.6006240249609984,
          "Error": 0.3993759750390016
        },
        "(0.22, 0.23]": {
          "Éxito": 0.5984126984126984,
          "Error": 0.4015873015873016
        },
        "(0.23, 0.24]": {
          "Éxito": 0.631911532385466,
          "Error": 0.36808846761453395
        },
        "(0.24, 0.25]": {
          "Éxito": 0.5735056542810986,
          "Error": 0.42649434571890144
        },
        "(0.25, 0.26]": {
          "Éxito": 0.575,
          "Error": 0.425
        },
        "(0.26, 0.27]": {
          "Éxito": 0.6293245469522241,
          "Error": 0.37067545304777594
        },
        "(0.27, 0.28]": {
          "Éxito": 0.6443381180223285,
          "Error": 0.35566188197767146
        },
        "(0.28, 0.29]": {
          "Éxito": 0.6189655172413793,
          "Error": 0.3810344827586207
        },
        "(0.29, 0.3]": {
          "Éxito": 0.622895622895623,
          "Error": 0.3771043771043771
        }
      }
    }
  }
}