{
  "experiment": {
    "name": "ARQ_2__ESC_1",
    "timestamp": "2025-06-19T08:58:33.152978",
    "repeat_index": 7
  },
  "effects": {
    "num_taps": {
      "is_categorical": true,
      "bins": null,
      "values": {
        "2": {
          "Éxito": 0.6131184895833334,
          "Error": 0.3868815104166667
        }
      }
    },
    "snr_db": {
      "is_categorical": false,
      "bins": 10,
      "values": {
        "(-0.00268, 0.401]": {
          "Éxito": 0.5993485342019544,
          "Error": 0.4006514657980456
        },
        "(0.401, 0.801]": {
          "Éxito": 0.6021505376344086,
          "Error": 0.3978494623655914
        },
        "(0.801, 1.201]": {
          "Éxito": 0.5548961424332344,
          "Error": 0.44510385756676557
        },
        "(1.201, 1.6]": {
          "Éxito": 0.6221122112211221,
          "Error": 0.3778877887788779
        },
        "(1.6, 2.0]": {
          "Éxito": 0.6258064516129033,
          "Error": 0.3741935483870968
        },
        "(2.0, 2.4]": {
          "Éxito": 0.5961227786752827,
          "Error": 0.40387722132471726
        },
        "(2.4, 2.799]": {
          "Éxito": 0.6366723259762309,
          "Error": 0.3633276740237691
        },
        "(2.799, 3.199]": {
          "Éxito": 0.6256499133448874,
          "Error": 0.37435008665511266
        },
        "(3.199, 3.599]": {
          "Éxito": 0.6245847176079734,
          "Error": 0.3754152823920266
        },
        "(3.599, 3.999]": {
          "Éxito": 0.6537162162162162,
          "Error": 0.34628378378378377
        }
      }
    },
    "phase_offset": {
      "is_categorical": false,
      "bins": 10,
      "values": {
        "(-0.0368, 4.506]": {
          "Éxito": 0.6150081566068516,
          "Error": 0.38499184339314846
        },
        "(4.506, 9.004]": {
          "Éxito": 0.606687898089172,
          "Error": 0.39331210191082805
        },
        "(9.004, 13.502]": {
          "Éxito": 0.6009771986970684,
          "Error": 0.3990228013029316
        },
        "(13.502, 17.999]": {
          "Éxito": 0.6195121951219512,
          "Error": 0.3804878048780488
        },
        "(17.999, 22.497]": {
          "Éxito": 0.643581081081081,
          "Error": 0.3564189189189189
        },
        "(22.497, 26.995]": {
          "Éxito": 0.6142857142857143,
          "Error": 0.38571428571428573
        },
        "(26.995, 31.493]": {
          "Éxito": 0.6035313001605136,
          "Error": 0.39646869983948635
        },
        "(31.493, 35.991]": {
          "Éxito": 0.6110183639398998,
          "Error": 0.38898163606010017
        },
        "(35.991, 40.488]": {
          "Éxito": 0.6125211505922166,
          "Error": 0.38747884940778343
        },
        "(40.488, 44.986]": {
          "Éxito": 0.6056338028169014,
          "Error": 0.39436619718309857
        }
      }
    },
    "roll_off": {
      "is_categorical": false,
      "bins": 10,
      "values": {
        "(0.2, 0.21]": {
          "Éxito": 0.6052202283849919,
          "Error": 0.39477977161500816
        },
        "(0.21, 0.22]": {
          "Éxito": 0.6131045241809673,
          "Error": 0.3868954758190328
        },
        "(0.22, 0.23]": {
          "Éxito": 0.6015873015873016,
          "Error": 0.3984126984126984
        },
        "(0.23, 0.24]": {
          "Éxito": 0.6334913112164297,
          "Error": 0.3665086887835703
        },
        "(0.24, 0.25]": {
          "Éxito": 0.5864297253634895,
          "Error": 0.4135702746365105
        },
        "(0.25, 0.26]": {
          "Éxito": 0.59,
          "Error": 0.41
        },
        "(0.26, 0.27]": {
          "Éxito": 0.6309719934102141,
          "Error": 0.36902800658978585
        },
        "(0.27, 0.28]": {
          "Éxito": 0.6236044657097288,
          "Error": 0.3763955342902711
        },
        "(0.28, 0.29]": {
          "Éxito": 0.6258620689655172,
          "Error": 0.3741379310344828
        },
        "(0.29, 0.3]": {
          "Éxito": 0.6212121212121212,
          "Error": 0.3787878787878788
        }
      }
    }
  }
}