{
  "experiment": {
    "name": "ARQ_3__ESC_1",
    "timestamp": "2025-06-19T07:18:53.198131",
    "repeat_index": 8
  },
  "effects": {
    "num_taps": {
      "is_categorical": true,
      "bins": null,
      "values": {
        "2": {
          "Éxito": 0.8001302083333334,
          "Error": 0.19986979166666666
        }
      }
    },
    "snr_db": {
      "is_categorical": false,
      "bins": 10,
      "values": {
        "(-0.00268, 0.401]": {
          "Éxito": 0.7817589576547231,
          "Error": 0.2182410423452769
        },
        "(0.401, 0.801]": {
          "Éxito": 0.7665130568356375,
          "Error": 0.23348694316436253
        },
        "(0.801, 1.201]": {
          "Éxito": 0.7507418397626113,
          "Error": 0.24925816023738873
        },
        "(1.201, 1.6]": {
          "Éxito": 0.7904290429042904,
          "Error": 0.20957095709570958
        },
        "(1.6, 2.0]": {
          "Éxito": 0.8209677419354838,
          "Error": 0.17903225806451614
        },
        "(2.0, 2.4]": {
          "Éxito": 0.7819063004846527,
          "Error": 0.21809369951534732
        },
        "(2.4, 2.799]": {
          "Éxito": 0.8387096774193549,
          "Error": 0.16129032258064516
        },
        "(2.799, 3.199]": {
          "Éxito": 0.8353552859618717,
          "Error": 0.16464471403812825
        },
        "(3.199, 3.599]": {
          "Éxito": 0.7956810631229236,
          "Error": 0.20431893687707642
        },
        "(3.599, 3.999]": {
          "Éxito": 0.8513513513513513,
          "Error": 0.14864864864864866
        }
      }
    },
    "phase_offset": {
      "is_categorical": false,
      "bins": 10,
      "values": {
        "(-0.0368, 4.506]": {
          "Éxito": 0.8172920065252854,
          "Error": 0.18270799347471453
        },
        "(4.506, 9.004]": {
          "Éxito": 0.7977707006369427,
          "Error": 0.20222929936305734
        },
        "(9.004, 13.502]": {
          "Éxito": 0.7817589576547231,
          "Error": 0.2182410423452769
        },
        "(13.502, 17.999]": {
          "Éxito": 0.7902439024390244,
          "Error": 0.2097560975609756
        },
        "(17.999, 22.497]": {
          "Éxito": 0.7871621621621622,
          "Error": 0.21283783783783783
        },
        "(22.497, 26.995]": {
          "Éxito": 0.7777777777777778,
          "Error": 0.2222222222222222
        },
        "(26.995, 31.493]": {
          "Éxito": 0.797752808988764,
          "Error": 0.20224719101123595
        },
        "(31.493, 35.991]": {
          "Éxito": 0.8247078464106845,
          "Error": 0.17529215358931552
        },
        "(35.991, 40.488]": {
          "Éxito": 0.8206429780033841,
          "Error": 0.1793570219966159
        },
        "(40.488, 44.986]": {
          "Éxito": 0.8075117370892019,
          "Error": 0.19248826291079812
        }
      }
    },
    "roll_off": {
      "is_categorical": false,
      "bins": 10,
      "values": {
        "(0.2, 0.21]": {
          "Éxito": 0.7830342577487766,
          "Error": 0.2169657422512235
        },
        "(0.21, 0.22]": {
          "Éxito": 0.8112324492979719,
          "Error": 0.18876755070202808
        },
        "(0.22, 0.23]": {
          "Éxito": 0.7777777777777778,
          "Error": 0.2222222222222222
        },
        "(0.23, 0.24]": {
          "Éxito": 0.8041074249605056,
          "Error": 0.19589257503949448
        },
        "(0.24, 0.25]": {
          "Éxito": 0.7754442649434572,
          "Error": 0.2245557350565428
        },
        "(0.25, 0.26]": {
          "Éxito": 0.795,
          "Error": 0.205
        },
        "(0.26, 0.27]": {
          "Éxito": 0.8220757825370676,
          "Error": 0.17792421746293247
        },
        "(0.27, 0.28]": {
          "Éxito": 0.8261562998405104,
          "Error": 0.17384370015948963
        },
        "(0.28, 0.29]": {
          "Éxito": 0.8086206896551724,
          "Error": 0.19137931034482758
        },
        "(0.29, 0.3]": {
          "Éxito": 0.797979797979798,
          "Error": 0.20202020202020202
        }
      }
    }
  }
}