{
  "experiment": {
    "name": "ARQ_3__ESC_8",
    "timestamp": "2025-06-19T18:25:44.832616",
    "repeat_index": 5
  },
  "effects": {
    "num_taps": {
      "is_categorical": true,
      "bins": null,
      "values": {
        "6": {
          "Éxito": 0.8427734375,
          "Error": 0.1572265625
        }
      }
    },
    "snr_db": {
      "is_categorical": false,
      "bins": 10,
      "values": {
        "(7.997, 8.4]": {
          "Éxito": 0.827922077922078,
          "Error": 0.17207792207792208
        },
        "(8.4, 8.8]": {
          "Éxito": 0.8122923588039868,
          "Error": 0.1877076411960133
        },
        "(8.8, 9.2]": {
          "Éxito": 0.8373205741626795,
          "Error": 0.16267942583732056
        },
        "(9.2, 9.6]": {
          "Éxito": 0.8369028006589786,
          "Error": 0.1630971993410214
        },
        "(9.6, 9.999]": {
          "Éxito": 0.862012987012987,
          "Error": 0.137987012987013
        },
        "(9.999, 10.399]": {
          "Éxito": 0.8383045525902669,
          "Error": 0.16169544740973313
        },
        "(10.399, 10.799]": {
          "Éxito": 0.8514548238897397,
          "Error": 0.14854517611026033
        },
        "(10.799, 11.199]": {
          "Éxito": 0.8632326820603907,
          "Error": 0.13676731793960922
        },
        "(11.199, 11.598]": {
          "Éxito": 0.85625,
          "Error": 0.14375
        },
        "(11.598, 11.998]": {
          "Éxito": 0.8421955403087479,
          "Error": 0.15780445969125215
        }
      }
    },
    "phase_offset": {
      "is_categorical": false,
      "bins": 10,
      "values": {
        "(-0.0382, 4.506]": {
          "Éxito": 0.8547854785478548,
          "Error": 0.14521452145214522
        },
        "(4.506, 9.005]": {
          "Éxito": 0.8396694214876033,
          "Error": 0.16033057851239668
        },
        "(9.005, 13.503]": {
          "Éxito": 0.8484848484848485,
          "Error": 0.15151515151515152
        },
        "(13.503, 18.002]": {
          "Éxito": 0.8477564102564102,
          "Error": 0.15224358974358973
        },
        "(18.002, 22.501]": {
          "Éxito": 0.8534923339011925,
          "Error": 0.1465076660988075
        },
        "(22.501, 27.0]": {
          "Éxito": 0.8455772113943029,
          "Error": 0.15442278860569716
        },
        "(27.0, 31.499]": {
          "Éxito": 0.835,
          "Error": 0.165
        },
        "(31.499, 35.998]": {
          "Éxito": 0.8283333333333334,
          "Error": 0.17166666666666666
        },
        "(35.998, 40.497]": {
          "Éxito": 0.8282504012841091,
          "Error": 0.17174959871589085
        },
        "(40.497, 44.996]": {
          "Éxito": 0.8462809917355372,
          "Error": 0.1537190082644628
        }
      }
    },
    "roll_off": {
      "is_categorical": false,
      "bins": 10,
      "values": {
        "(0.2, 0.21]": {
          "Éxito": 0.8221830985915493,
          "Error": 0.17781690140845072
        },
        "(0.21, 0.22]": {
          "Éxito": 0.8432343234323433,
          "Error": 0.15676567656765678
        },
        "(0.22, 0.23]": {
          "Éxito": 0.8431372549019608,
          "Error": 0.1568627450980392
        },
        "(0.23, 0.24]": {
          "Éxito": 0.8576104746317512,
          "Error": 0.14238952536824878
        },
        "(0.24, 0.25]": {
          "Éxito": 0.8210180623973727,
          "Error": 0.17898193760262726
        },
        "(0.25, 0.26]": {
          "Éxito": 0.8429003021148036,
          "Error": 0.15709969788519637
        },
        "(0.26, 0.27]": {
          "Éxito": 0.8455538221528861,
          "Error": 0.1544461778471139
        },
        "(0.27, 0.28]": {
          "Éxito": 0.8665568369028006,
          "Error": 0.13344316309719934
        },
        "(0.28, 0.29]": {
          "Éxito": 0.8494271685761048,
          "Error": 0.15057283142389524
        },
        "(0.29, 0.3]": {
          "Éxito": 0.8346839546191248,
          "Error": 0.16531604538087522
        }
      }
    }
  }
}